{
  "sido": "서울특별시",
  "sigungu": "광진구",
  "totalCount": 11,
  "items": [
    {
      "name": "자양유수지",
      "type": "공영",
      "category": "노외",
      "address": "서울특별시 광진구 뚝섬로52길 58",
      "lat": 37.52966146352903,
      "lng": 127.07761018399374,
      "totalSpaces": 281,
      "isFree": false,
      "operatingDays": "평일+토요일+공휴일",
      "weekdayOpen": "00:00",
      "weekdayClose": "23:59",
      "weekendOpen": "00:00",
      "weekendClose": "23:59",
      "holidayOpen": "00:00",
      "holidayClose": "23:59",
      "feeInfo": "기본 5분 200원 / 추가 5분당 200원",
      "phone": "02-2049-4535",
      "updatedAt": "2025-11-05",
      "sido": "서울특별시",
      "sigungu": "광진구",
      "dong": "자양동",
      "roadAddress": "서울 광진구 뚝섬로52길 58",
      "kakaoPhone": "02-2049-4595",
      "kakaoName": "자양유수지 공영주차장",
      "kakaoVerified": true,
      "naverPlaceId": "1818015545",
      "naverName": "자양유수지 노상 공영 주차장",
      "naverPhone": "02-2049-4540",
      "naverAddress": "서울특별시 광진구 자양동 594",
      "naverRoadAddress": "서울특별시 광진구 뚝섬로52길 74-1",
      "naverX": "127.0776666",
      "naverY": "37.5296746",
      "naverVerified": true
    },
    {
      "name": "구의1동 공영주차장",
      "type": "공영",
      "category": "노외",
      "address": "서울특별시 광진구 자양로18길 78",
      "lat": 37.53826965,
      "lng": 127.0878657,
      "totalSpaces": 172,
      "isFree": false,
      "operatingDays": "평일+토요일+공휴일",
      "weekdayOpen": "00:00",
      "weekdayClose": "23:59",
      "weekendOpen": "00:00",
      "weekendClose": "23:59",
      "holidayOpen": "00:00",
      "holidayClose": "23:59",
      "feeInfo": "기본 5분 200원 / 추가 5분당 200원",
      "phone": "02-2049-4535",
      "updatedAt": "2025-11-05",
      "sido": "서울특별시",
      "sigungu": "광진구",
      "dong": "구의동",
      "roadAddress": "서울 광진구 자양로18길 78",
      "kakaoPhone": "02-453-2028",
      "kakaoName": "구의1동 공영주차장",
      "kakaoVerified": true,
      "naverPlaceId": "35992895",
      "naverName": "구의1동공영주차장",
      "naverAddress": "서울특별시 광진구 구의동 243-78",
      "naverRoadAddress": "서울특별시 광진구 자양로18길 78",
      "naverX": "127.0878866",
      "naverY": "37.5383242",
      "naverVerified": true
    },
    {
      "name": "중곡3동 마을공원 공영주차장",
      "type": "공영",
      "category": "노외",
      "address": "서울특별시 광진구 용마산로33길 25",
      "lat": 37.56991861,
      "lng": 127.0846836,
      "totalSpaces": 162,
      "isFree": false,
      "operatingDays": "평일+토요일+공휴일",
      "weekdayOpen": "00:00",
      "weekdayClose": "23:59",
      "weekendOpen": "00:00",
      "weekendClose": "23:59",
      "holidayOpen": "00:00",
      "holidayClose": "23:59",
      "feeInfo": "기본 5분 150원 / 추가 5분당 150원",
      "phone": "02-2049-4535",
      "updatedAt": "2025-11-05",
      "sido": "서울특별시",
      "sigungu": "광진구",
      "dong": "중곡동",
      "roadAddress": "서울 광진구 용마산로33길 25",
      "kakaoName": "중곡3동 마을공원공영주차장",
      "kakaoVerified": true,
      "naverPlaceId": "1006965782",
      "naverName": "중곡3동1마을공원공영주차장",
      "naverAddress": "서울특별시 광진구 중곡동 195-1",
      "naverRoadAddress": "서울특별시 광진구 용마산로33길 25",
      "naverX": "127.0845467",
      "naverY": "37.5700888",
      "naverVerified": true
    },
    {
      "name": "구의3동 공영주차장",
      "type": "공영",
      "category": "노외",
      "address": "서울특별시 광진구 광나루로52길 83",
      "lat": 37.53915358,
      "lng": 127.0913608,
      "totalSpaces": 159,
      "isFree": false,
      "operatingDays": "평일+토요일+공휴일",
      "weekdayOpen": "00:00",
      "weekdayClose": "23:59",
      "weekendOpen": "00:00",
      "weekendClose": "23:59",
      "holidayOpen": "00:00",
      "holidayClose": "23:59",
      "feeInfo": "기본 5분 200원 / 추가 5분당 200원",
      "phone": "02-2049-4535",
      "updatedAt": "2025-11-05",
      "sido": "서울특별시",
      "sigungu": "광진구",
      "dong": "구의동",
      "roadAddress": "서울 광진구 광나루로52길 83",
      "kakaoPhone": "02-2049-4595",
      "kakaoName": "구의3동 공영주차장",
      "kakaoVerified": true,
      "naverPlaceId": "18816578",
      "naverName": "구의3동공영주차장",
      "naverAddress": "서울특별시 광진구 구의동 219-15",
      "naverRoadAddress": "서울특별시 광진구 광나루로52길 83",
      "naverX": "127.0914082",
      "naverY": "37.5391857",
      "naverVerified": true
    },
    {
      "name": "구의2동 주택가공동 주차장",
      "type": "공영",
      "category": "노외",
      "address": "서울특별시 광진구 자양로 307",
      "lat": 37.5529341,
      "lng": 127.0928443,
      "totalSpaces": 90,
      "isFree": false,
      "operatingDays": "평일+토요일+공휴일",
      "weekdayOpen": "09:00",
      "weekdayClose": "18:00",
      "weekendOpen": "08:00",
      "weekendClose": "18:00",
      "holidayOpen": "00:00",
      "holidayClose": "18:00",
      "feeInfo": "기본 5분 150원 / 추가 5분당 150원",
      "phone": "02-2049-4535",
      "updatedAt": "2025-11-05",
      "sido": "서울특별시",
      "sigungu": "광진구",
      "dong": "구의동",
      "roadAddress": "서울 광진구 자양로 307",
      "kakaoPhone": "02-2049-4595",
      "kakaoName": "구의2동주택가 공동주차장",
      "kakaoVerified": true,
      "naverPlaceId": "226115480",
      "naverName": "구의2동주택가공동주차장",
      "naverPhone": "02-2049-4595",
      "naverAddress": "서울특별시 광진구 구의동 30-9",
      "naverRoadAddress": "서울특별시 광진구 자양로 307",
      "naverX": "127.0928143",
      "naverY": "37.5529766",
      "naverVerified": true
    },
    {
      "name": "자양4동 공영",
      "type": "공영",
      "category": "노외",
      "address": "서울특별시 광진구 자양동 5-5",
      "lat": 37.53864952,
      "lng": 127.0681734,
      "totalSpaces": 83,
      "isFree": false,
      "operatingDays": "평일+토요일+공휴일",
      "weekdayOpen": "00:00",
      "weekdayClose": "23:59",
      "weekendOpen": "00:00",
      "weekendClose": "23:59",
      "holidayOpen": "00:00",
      "holidayClose": "23:59",
      "feeInfo": "기본 5분 250원 / 추가 5분당 250원",
      "phone": "02-2049-4535",
      "updatedAt": "2025-11-05",
      "sido": "서울특별시",
      "sigungu": "광진구",
      "dong": "자양동",
      "kakaoPhone": "02-2049-4595",
      "kakaoName": "자양4동 공영주차장",
      "kakaoVerified": true,
      "naverPlaceId": "21185991",
      "naverName": "자양4동공영주차장",
      "naverPhone": "02-2049-4595",
      "naverAddress": "서울특별시 광진구 자양동 5-5",
      "naverX": "127.0681855",
      "naverY": "37.5386904",
      "naverVerified": true
    },
    {
      "name": "구의2동 복합청사 공영주차장",
      "type": "공영",
      "category": "노외",
      "address": "서울특별시 광진구 천호대로136길 55",
      "lat": 37.5479409672484,
      "lng": 127.090262535314,
      "totalSpaces": 81,
      "isFree": false,
      "operatingDays": "평일+토요일+공휴일",
      "weekdayOpen": "00:00",
      "weekdayClose": "23:59",
      "weekendOpen": "00:00",
      "weekendClose": "23:59",
      "holidayOpen": "00:00",
      "holidayClose": "23:59",
      "feeInfo": "기본 5분 200원 / 추가 5분당 200원",
      "phone": "02-2049-4535",
      "updatedAt": "2025-11-05",
      "sido": "서울특별시",
      "sigungu": "광진구",
      "dong": "구의동",
      "roadAddress": "서울 광진구 천호대로136길 55",
      "kakaoName": "광진구구의동주차장",
      "kakaoVerified": true,
      "naverPlaceId": "1055480485",
      "naverName": "구의2동 복합청사 지하주차장",
      "naverAddress": "서울특별시 광진구 구의동 63-6",
      "naverRoadAddress": "서울특별시 광진구 천호대로136길 55",
      "naverX": "127.0899571",
      "naverY": "37.5471482",
      "naverVerified": true
    },
    {
      "name": "능동 공영주차장",
      "type": "공영",
      "category": "노외",
      "address": "서울특별시 광진구 천호대로112길 56",
      "lat": 37.55404255,
      "lng": 127.0802429,
      "totalSpaces": 77,
      "isFree": false,
      "operatingDays": "평일+토요일+공휴일",
      "weekdayOpen": "00:00",
      "weekdayClose": "23:59",
      "weekendOpen": "00:00",
      "weekendClose": "23:59",
      "holidayOpen": "00:00",
      "holidayClose": "23:59",
      "feeInfo": "기본 5분 200원 / 추가 5분당 200원",
      "phone": "02-2049-4535",
      "updatedAt": "2025-11-05",
      "sido": "서울특별시",
      "sigungu": "광진구",
      "dong": "능동",
      "roadAddress": "서울 광진구 천호대로112길 56",
      "kakaoPhone": "02-2049-4595",
      "kakaoName": "능동공영주차장",
      "kakaoVerified": true,
      "naverPlaceId": "18810610",
      "naverName": "능동공영주차장",
      "naverPhone": "02-2049-4595",
      "naverAddress": "서울특별시 광진구 능동 205",
      "naverRoadAddress": "서울특별시 광진구 천호대로112길 56",
      "naverX": "127.0803494",
      "naverY": "37.5540552",
      "naverVerified": true
    },
    {
      "name": "화양동 공영",
      "type": "공영",
      "category": "노외",
      "address": "서울특별시 광진구 군자로 22",
      "lat": 37.54529787,
      "lng": 127.0711809,
      "totalSpaces": 44,
      "isFree": false,
      "operatingDays": "평일+토요일+공휴일",
      "weekdayOpen": "00:00",
      "weekdayClose": "23:59",
      "weekendOpen": "00:00",
      "weekendClose": "23:59",
      "holidayOpen": "00:00",
      "holidayClose": "23:59",
      "feeInfo": "기본 5분 200원 / 추가 5분당 200원",
      "phone": "02-2049-4535",
      "updatedAt": "2025-11-05",
      "sido": "서울특별시",
      "sigungu": "광진구",
      "dong": "화양동",
      "roadAddress": "서울 광진구 군자로 22",
      "kakaoPhone": "02-469-2939",
      "kakaoName": "화양동 공영주차장",
      "kakaoVerified": true,
      "naverPlaceId": "2145499999",
      "naverName": "화양동 공영주차장",
      "naverAddress": "서울특별시 광진구 화양동 63-2",
      "naverRoadAddress": "서울특별시 광진구 군자로 22",
      "naverX": "127.0711495",
      "naverY": "37.5452699",
      "naverVerified": true
    },
    {
      "name": "광진광장 공영",
      "type": "공영",
      "category": "노외",
      "address": "서울특별시 광진구 광나루로 389",
      "lat": 37.54769328,
      "lng": 127.0732156,
      "totalSpaces": 33,
      "isFree": false,
      "operatingDays": "평일+토요일+공휴일",
      "weekdayOpen": "00:00",
      "weekdayClose": "23:59",
      "weekendOpen": "00:00",
      "weekendClose": "23:59",
      "holidayOpen": "00:00",
      "holidayClose": "23:59",
      "feeInfo": "기본 5분 250원 / 추가 5분당 250원",
      "phone": "02-2049-4535",
      "updatedAt": "2025-11-05",
      "sido": "서울특별시",
      "sigungu": "광진구",
      "dong": "군자동",
      "roadAddress": "서울 광진구 광나루로 389",
      "kakaoPhone": "02-2049-4595",
      "kakaoName": "광진광장 공영주차장",
      "kakaoVerified": true,
      "naverPlaceId": "21185766",
      "naverName": "광진광장공영주차장",
      "naverPhone": "02-465-2026",
      "naverAddress": "서울특별시 광진구 군자동 374-4",
      "naverRoadAddress": "서울특별시 광진구 광나루로 389",
      "naverX": "127.0731127",
      "naverY": "37.5477560",
      "naverVerified": true
    },
    {
      "name": "올림픽대교(북)",
      "type": "공영",
      "category": "노상",
      "address": "서울특별시 광진구 구의동 올림픽대교(하부)",
      "lat": 37.5339619,
      "lng": 127.1016861,
      "totalSpaces": 19,
      "isFree": false,
      "operatingDays": "평일+토요일+공휴일",
      "weekdayOpen": "00:00",
      "weekdayClose": "00:00",
      "weekendOpen": "00:00",
      "weekendClose": "00:00",
      "holidayOpen": "00:00",
      "holidayClose": "00:00",
      "feeInfo": "기본 5분 0원",
      "phone": "",
      "updatedAt": "2021-07-30",
      "sido": "서울특별시",
      "sigungu": "광진구",
      "dong": "구의동",
      "kakaoVerified": false,
      "naverVerified": false
    }
  ]
}
